sessypy/__init__.py
sessypy/api.py
sessypy/const.py
sessypy/devices.py
sessypy/util.py
sessypy-0.2.4.dist-info/licenses/LICENSE
sessypy-0.2.4.dist-info/METADATA
sessypy-0.2.4.dist-info/WHEEL
sessypy-0.2.4.dist-info/top_level.txt
sessypy-0.2.4.dist-info/RECORD
