Metadata-Version: 2.4
Name: sessypy
Version: 0.2.4
Summary: Python wrapper for Sessy REST API
Home-page: https://github.com/PimDoos/sessypy
Author: PimDoos
License:                     GNU GENERAL PUBLIC LICENSE
Project-URL: Homepage, https://github.com/PimDoos/sessypy
License-File: LICENSE
Dynamic: license-file
